biosimulators_bionetgen/__init__.py
biosimulators_bionetgen/__main__.py
biosimulators_bionetgen/_version.py
biosimulators_bionetgen/config.py
biosimulators_bionetgen/core.py
biosimulators_bionetgen/data_model.py
biosimulators_bionetgen/io.py
biosimulators_bionetgen/utils.py
biosimulators_bionetgen/warnings.py
biosimulators_bionetgen-0.1.20.dist-info/LICENSE
biosimulators_bionetgen-0.1.20.dist-info/METADATA
biosimulators_bionetgen-0.1.20.dist-info/WHEEL
biosimulators_bionetgen-0.1.20.dist-info/entry_points.txt
biosimulators_bionetgen-0.1.20.dist-info/top_level.txt
biosimulators_bionetgen-0.1.20.dist-info/RECORD
