Metadata-Version: 2.1
Name: biosimulators-bionetgen
Version: 0.1.20
Summary: BioSimulators-compliant command-line interface to the BioNetGen simulation program <https://bionetgen.org>.
Home-page: https://github.com/biosimulators/Biosimulators_BioNetGen
Download-URL: https://github.com/biosimulators/Biosimulators_BioNetGen
Author: BioSimulators Team
Author-email: info@biosimulators.org
License: MIT
Keywords: systems biology,rule-based modeling,network-free simulation,kinetic modeling,numerical simulation,BioNetGen,BioSimulators,SED-ML,COMBINE,OMEX
Platform: UNKNOWN
Classifier: Development Status :: 3 - Alpha
Classifier: Intended Audience :: Science/Research
Classifier: License :: OSI Approved :: MIT License
Classifier: Topic :: Scientific/Engineering :: Bio-Informatics
License-File: LICENSE
Requires-Dist: biosimulators-utils[bngl,logging] (>=0.1.124)
Requires-Dist: kisao (>=2.29)
Requires-Dist: pandas
Provides-Extra: all
Requires-Dist: biosimulators-utils[containers] ; extra == 'all'
Requires-Dist: numpy ; extra == 'all'
Requires-Dist: pytest ; extra == 'all'
Requires-Dist: python-dateutil ; extra == 'all'
Provides-Extra: docs
Provides-Extra: tests
Requires-Dist: biosimulators-utils[containers] ; extra == 'tests'
Requires-Dist: numpy ; extra == 'tests'
Requires-Dist: pytest ; extra == 'tests'
Requires-Dist: python-dateutil ; extra == 'tests'
